magerestore/__init__.py
magerestore/app.py
magerestore/cli.py
magerestore/config.py
magerestore/repository.py
magerestore/resource.py
magerestore-0.1.1.dist-info/DESCRIPTION.rst
magerestore-0.1.1.dist-info/METADATA
magerestore-0.1.1.dist-info/RECORD
magerestore-0.1.1.dist-info/WHEEL
magerestore-0.1.1.dist-info/entry_points.txt
magerestore-0.1.1.dist-info/metadata.json
magerestore-0.1.1.dist-info/top_level.txt
